{
  "courseId": "tech-sciences-1",
  "courseTitle": {
    "en": "Introduction to Technical Sciences",
    "ar": "مقدمة في العلوم التقنية"
  },
  "items": [
    {
      "id": "lesson-1",
      "title": {
        "en": "Foundations of Logic Gates",
        "ar": "أساسيات البوابات المنطقية"
      },
      "type": "text",
      "content": {
        "en": "endlish",
        "ar": "عربي"
      },
      "points": 10
    },
    {
      "id": "lesson-2",
      "title": {
        "en": "Combinational Logic Circuits",
        "ar": "الدوائر المنطقية التجميعية"
      },
      "type": "text",
      "content": {
        "en": "english \n\n image: ![text image](https://raw.githubusercontent.com/AbdelkaderHazerchi/Learnano/refs/heads/main/ccc.jpg)",
        "ar": "عربي صورة: ![text image](https://raw.githubusercontent.com/AbdelkaderHazerchi/Learnano/refs/heads/main/ccc.jpg)"
      },
      "points": 10
    },
    {
      "id": "quiz-1",
      "title": {
        "en": "Logic Gates Checkpoint Quiz",
        "ar": "اختبار البوابات المنطقية"
      },
      "type": "quiz",
      "points": 25,
      "passThreshold": 0.8,
      "questions": [
        {
          "questionId": "q1",
          "questionText": {
            "en": "Which logic gate outputs a high signal (1) only when all inputs are low (0)?",
            "ar": "أي بوابة منطقية تخرج إشارة عالية (1) فقط عندما تكون جميع المدخلات منخفضة (0)؟"
          },
          "type": "single",
          "options": {
            "en": ["AND Gate", "NOR Gate", "OR Gate", "NAND Gate"],
            "ar": ["بوابة AND", "بوابة NOR", "بوابة OR", "بوابة NAND"]
          },
          "correctAnswerIndex": 1
        },
        {
          "questionId": "q2",
          "questionText": {
            "en": "What does a NOT gate do?",
            "ar": "ماذا تفعل بوابة NOT؟"
          },
          "type": "single",
          "options": {
            "en": ["Multiplies inputs", "Inverts the input", "Adds two inputs", "Stores a bit"],
            "ar": ["تضاعف المدخلات", "تعكس الإدخال", "تجمع مدخلين", "تخزن بتًا"]
          },
          "correctAnswerIndex": 1
        },
        {
          "questionId": "q3",
          "questionText": {
            "en": "Select all statements that are TRUE about an AND gate:",
            "ar": "اختر جميع العبارات الصحيحة حول بوابة AND:"
          },
          "type": "multiple",
          "options": {
            "en": [
              "Output is 1 only when ALL inputs are 1",
              "Output is 1 when at least one input is 1",
              "It can have two or more inputs",
              "It is the same as an OR gate"
            ],
            "ar": [
              "المخرج يكون 1 فقط عندما تكون جميع المدخلات 1",
              "المخرج يكون 1 عندما يكون إدخال واحد على الأقل 1",
              "يمكن أن يكون لها مدخلان أو أكثر",
              "هي نفس بوابة OR"
            ]
          },
          "correctAnswerIndices": [0, 2]
        }
      ]
    }
  ]
}
